dict_objectify/__init__.py
dict_objectify/base/__init__.py
dict_objectify/base/base.py
dict_objectify/base/constants.py
dict_objectify/base/field_base.py
dict_objectify/base/hash.py
dict_objectify/fields/__init__.py
dict_objectify/fields/array.py
dict_objectify/fields/bool.py
dict_objectify/fields/date.py
dict_objectify/fields/enum.py
dict_objectify/fields/float.py
dict_objectify/fields/integer.py
dict_objectify/fields/text.py
dict_objectify-0.0.2.dist-info/LICENSE
dict_objectify-0.0.2.dist-info/METADATA
dict_objectify-0.0.2.dist-info/WHEEL
dict_objectify-0.0.2.dist-info/top_level.txt
dict_objectify-0.0.2.dist-info/RECORD
