Metadata-Version: 2.1
Name: dict-objectify
Version: 0.0.2
Summary: Dictionary to Object hierarchy mapper.
Home-page: https://github.com/reljicd/dict-objectify
Author: Dusan Reljic
Author-email: reljicd@google.com
License: Apache Software License
Keywords: mapper mapping dict dictionary object oop xml json csv
Classifier: Development Status :: 4 - Beta
Classifier: Intended Audience :: Developers
Classifier: Topic :: Software Development :: Libraries :: Python Modules
Classifier: License :: OSI Approved :: Apache Software License
Classifier: Programming Language :: Python
Classifier: Programming Language :: Python :: 3
Classifier: Programming Language :: Python :: 3.5
Classifier: Programming Language :: Python :: 3.6
Classifier: Programming Language :: Python :: 3.7
Classifier: Programming Language :: Python :: 3.8
Classifier: Programming Language :: Python :: 3.9
Classifier: Operating System :: OS Independent
Classifier: Operating System :: POSIX
Classifier: Operating System :: MacOS
Classifier: Operating System :: Unix
License-File: LICENSE
Requires-Dist: str2bool
